delimiters/__init__.py
delimiters/api.py
delimiters/custom_markdown.py
delimiters/html_ext.py
delimiters/markdown_ext.py
delimiters-0.1.3.dist-info/licenses/LICENSE
delimiters-0.1.3.dist-info/METADATA
delimiters-0.1.3.dist-info/WHEEL
delimiters-0.1.3.dist-info/top_level.txt
delimiters-0.1.3.dist-info/RECORD
