Metadata-Version: 2.4
Name: delimiters
Version: 0.1.3
Summary: Advanced formatting add-ons for Telethon with predictable Markdown and HTML parsing
Home-page: https://github.com/ankit-chaubey/delimiters
Author: Ankit Chaubey
Author-email: m.ankitchaubey@gmail.com
Project-URL: Source, https://github.com/ankit-chaubey/delimiters
Project-URL: Bug Tracker, https://github.com/ankit-chaubey/delimiters/issues
Project-URL: Documentation, https://github.com/ankit-chaubey/delimiters#readme
Keywords: telegram,telethon,markdown,html,parser,entities,formatting,delimiters
Classifier: Development Status :: 3 - Alpha
Classifier: Intended Audience :: Developers
Classifier: Topic :: Communications :: Chat
Classifier: Topic :: Software Development :: Libraries
Classifier: Programming Language :: Python :: 3
Classifier: Programming Language :: Python :: 3 :: Only
Classifier: License :: Other/Proprietary License
Classifier: Operating System :: OS Independent
Requires-Python: >=3.9
License-File: LICENSE
Requires-Dist: telethon>=1.34.0
Dynamic: author
Dynamic: author-email
Dynamic: classifier
Dynamic: description
Dynamic: description-content-type
Dynamic: home-page
Dynamic: keywords
Dynamic: license-file
Dynamic: project-url
Dynamic: requires-dist
Dynamic: requires-python
Dynamic: summary
